MANIFEST.in
README-PYPI.rst
setup.py
galaxygetopt/__init__.py
galaxygetopt/exceptions.py
galaxygetopt/galaxy.py
galaxygetopt/ggo.py
galaxygetopt/outputfiles.py
galaxygetopt/pc.py
galaxygetopt/tg.py
galaxygetopt.egg-info/PKG-INFO
galaxygetopt.egg-info/SOURCES.txt
galaxygetopt.egg-info/dependency_links.txt
galaxygetopt.egg-info/requires.txt
galaxygetopt.egg-info/top_level.txt
galaxygetopt/parameter/__init__.py
galaxygetopt/parameter/empty.py
galaxygetopt/parameter/fileinput.py
galaxygetopt/parameter/fileoutput.py
galaxygetopt/parameter/fileoutputformat.py
galaxygetopt/parameter/flag.py
galaxygetopt/parameter/float.py
galaxygetopt/parameter/genomictagoption.py
galaxygetopt/parameter/int.py
galaxygetopt/parameter/label.py
galaxygetopt/parameter/option.py
galaxygetopt/parameter/parameter.py
galaxygetopt/parameter/string.py
galaxygetopt/writer/__init__.py
galaxygetopt/writer/csv_u.py
galaxygetopt/writer/csv_w.py
galaxygetopt/writer/dummy.py
galaxygetopt/writer/fasta.py
galaxygetopt/writer/genbank.py
galaxygetopt/writer/html.py
galaxygetopt/writer/tsv.py
galaxygetopt/writer/tsv_u.py
galaxygetopt/writer/txt.py
galaxygetopt/writer/writer.py