Metadata-Version: 1.1
Name: galaxygetopt
Version: 0.9.7
Summary: Argparse Wrapper for Galaxy
Home-page: https://cpt.tamu.edu/gitlab/cpt/pygetoptwrapper/
Author: Eric Rasche
Author-email: rasche.eric@yandex.ru
License: GPL3
Platform: UNKNOWN
Classifier: Development Status :: 4 - Beta
Classifier: Operating System :: OS Independent
Classifier: Intended Audience :: Developers
Classifier: Environment :: Console
